{
  "project_info": {
    "project_number": "165573874763",
    "project_id": "chat-app-firebase-c4dc6",
    "storage_bucket": "chat-app-firebase-c4dc6.appspot.com"
  },
  "client": [
    {
      "client_info": {
        "mobilesdk_app_id": "1:165573874763:android:db204320548ddbdad2a9ce",
        "android_client_info": {
          "package_name": "com.example.chat_app_firebase"
        }
      },
      "oauth_client": [],
      "api_key": [
        {
          "current_key": "AIzaSyDx71nIsGVmxAhHMmONrLvWRGQg1MBWR3c"
        }
      ],
      "services": {
        "appinvite_service": {
          "other_platform_oauth_client": []
        }
      }
    }
  ],
  "configuration_version": "1"
}